{
  "hash": "b631c863",
  "configHash": "f119ae4a",
  "lockfileHash": "4d026c2d",
  "browserHash": "629a938e",
  "optimized": {
    "vue": {
      "src": "../../../node_modules/vue/dist/vue.runtime.esm-bundler.js",
      "file": "vue.js",
      "fileHash": "ee2d322c",
      "needsInterop": false
    },
    "vitepress > @vue/devtools-api": {
      "src": "../../../node_modules/@vue/devtools-api/dist/index.js",
      "file": "vitepress___@vue_devtools-api.js",
      "fileHash": "d9b026bb",
      "needsInterop": false
    },
    "vitepress > @vueuse/core": {
      "src": "../../../node_modules/@vueuse/core/index.mjs",
      "file": "vitepress___@vueuse_core.js",
      "fileHash": "83017436",
      "needsInterop": false
    }
  },
  "chunks": {
    "chunk-QPQFSO6H": {
      "file": "chunk-QPQFSO6H.js"
    }
  }
}